autodiscjax/__init__.py
autodiscjax/dictree.py
autodiscjax/module.py
autodiscjax/experiment_pipelines/__init__.py
autodiscjax/experiment_pipelines/imgep_experiment_pipeline.py
autodiscjax/experiment_pipelines/robustness_evaluation_pipeline.py
autodiscjax/experiment_pipelines/rs_experiment_pipeline.py
autodiscjax/modules/__init__.py
autodiscjax/modules/grnwrappers.py
autodiscjax/modules/imgepwrappers.py
autodiscjax/modules/misc.py
autodiscjax/modules/optimizers.py
autodiscjax/utils/__init__.py
autodiscjax/utils/accessors.py
autodiscjax/utils/create_modules.py
autodiscjax/utils/logging.py
autodiscjax/utils/misc.py
autodiscjax/utils/timeseries.py
autodiscjax-0.4.1.dist-info/LICENSE
autodiscjax-0.4.1.dist-info/METADATA
autodiscjax-0.4.1.dist-info/WHEEL
autodiscjax-0.4.1.dist-info/top_level.txt
autodiscjax-0.4.1.dist-info/RECORD
