Metadata-Version: 2.1
Name: autodiscjax
Version: 0.4.1
Summary: python library built on top of jax to facilitate automated exploration and simulation of computational models of biological processes
Home-page: https://github.com/flowersteam/autodiscjax
Author: Mayalen Etcheverry
Author-email: mayalen.etcheverry@inria.fr
License: MIT
Classifier: Programming Language :: Python :: 3
Classifier: License :: OSI Approved :: MIT License
Classifier: Operating System :: OS Independent
License-File: LICENSE
Requires-Dist: jax[cpu]
Requires-Dist: optax
Requires-Dist: equinox
Requires-Dist: addict
